{
	"response": [
		{
			"maintainer": "zizzyboi",
			"oem": "OnePlus",
			"device": "9R",
			"filename": "AlphaDroid-14.0-20240519-lemonades-microg-v2.1.zip",
			"download": "https://sourceforge.net/projects/alphadroid-project/files/lemonades/AlphaDroid-14.0-20240519-lemonades-microg-v2.1.zip/download",
			"timestamp": 1716081172,
			"md5": "ac4ae545d033c9b9fb9e858224fe6d6e",
			"sha256": "b59a05363090a8005fcfa951096dd103df17ff4619bac442a40e57c5d0e3dce7",
			"size": 1791692213,
			"version": "2.1",
			"buildtype": "microg",
			"forum": "",
			"gapps": "",
			"firmware": "",
			"modem": "",
			"bootloader": "",
			"recovery": "",
			"paypal": "https://paypal.me/zizzyboi?country.x=CA&locale.x=en_US",
			"telegram": "https://t.me/zahidsromfactory",
			"dt": "",
			"common-dt": "",
			"kernel": ""
			},
			{
			"maintainer": "zizzyboi",
			"oem": "OnePlus",
			"device": "9R",
			"filename": "AlphaDroid-14.0-20240518-lemonades-gapps-v2.1.zip",
			"download": "https://sourceforge.net/projects/alphadroid-project/files/lemonades/AlphaDroid-14.0-20240518-lemonades-gapps-v2.1.zip/download",
			"timestamp": 1716062888,
			"md5": "052522092649dd50a438a3dd83069ce9",
			"sha256": "35536d62378b750140223db45cf171df8e1c8a133084f7e1f0e74fa6b1fe0265",
			"size": 2266914323,
			"version": "2.1",
			"buildtype": "gapps",
			"forum": "",
			"gapps": "",
			"firmware": "",
			"modem": "",
			"bootloader": "",
			"recovery": "",
			"paypal": "https://paypal.me/zizzyboi?country.x=CA&locale.x=en_US",
			"telegram": "https://t.me/zahidsromfactory",
			"dt": "",
			"common-dt": "",
			"kernel": ""
			},
			{
			"maintainer": "zizzyboi",
			"oem": "OnePlus",
			"device": "9R",
			"filename": "AlphaDroid-14.0-20240518-lemonades-vanilla-v2.1.zip",
			"download": "https://sourceforge.net/projects/alphadroid-project/files/lemonades/AlphaDroid-14.0-20240518-lemonades-vanilla-v2.1.zip/download",
			"timestamp": 1716014819,
			"md5": "b4318ed1f2c14401487ce10c3373fefb",
			"sha256": "0beb8963660616e5861e4d83545396da861812a79126213b231ef25e8b0df75d",
			"size": 1753410058,
			"version": "2.1",
			"buildtype": "vanilla",
			"forum": "",
			"gapps": "",
			"firmware": "",
			"modem": "",
			"bootloader": "",
			"recovery": "",
			"paypal": "https://paypal.me/zizzyboi?country.x=CA&locale.x=en_US",
			"telegram": "https://t.me/zahidsromfactory",
			"dt": "",
			"common-dt": "",
			"kernel": ""
		}
	]
}
