{
	"response": [
		{
			"maintainer": "eklerismunir",
			"oem": "Xiaomi",
			"device": "Xiaomi Redmi Note 10",
			"filename": "AlphaDroid-14.0-20240807-sunny-vanilla-v2.3.zip",
			"download": "https://sourceforge.net/projects/alphadroid-project/files/sunny/AlphaDroid-14.0-20240807-sunny-vanilla-v2.3.zip/download",
			"timestamp": 1723010911,
			"md5": "171f74e47dc5b2486a66d26b782f77e7",
			"sha256": "127ace204523882e62f69b67f07ff9b605e43f850df072e3107f70439e95fb19",
			"size": 1475566340,
			"version": "2.3",
			"buildtype": "vanilla",
			"forum": "https://t.me/alphadroid_chat",
			"gapps": "",
			"firmware": "",
			"modem": "",
			"bootloader": "",
			"recovery": "",
			"paypal": "",
			"telegram": "https://t.me/shawkbuilddiscussion",
			"dt": "https://github.com/AlphaDroid-devices/device_xiaomi_sunny/tree/alpha-14",
			"common-dt": "",
			"kernel": "https://github.com/Neternels/android_kernel_xiaomi_sunny/tree/staging"
		},
		{
			"maintainer": "eklerismunir",
			"oem": "Xiaomi",
			"device": "Xiaomi Redmi Note 10",
			"filename": "AlphaDroid-14.0-20240807-sunny-microg-v2.3.zip",
			"download": "https://sourceforge.net/projects/alphadroid-project/files/sunny/AlphaDroid-14.0-20240807-sunny-microg-v2.3.zip/download",
			"timestamp": 1723069979,
			"md5": "85141b41e487af24a5a8757915a8e7cb",
			"sha256": "8d593e396cc2e4f55174e1641ba455ca4c0496a86c6fe730eac06e79313109d3",
			"size": 1546912518,
			"version": "2.3",
			"buildtype": "microg",
			"forum": "https://t.me/alphadroid_chat",
			"gapps": "",
			"firmware": "",
			"modem": "",
			"bootloader": "",
			"recovery": "",
			"paypal": "",
			"telegram": "https://t.me/shawkbuilddiscussion",
			"dt": "https://github.com/AlphaDroid-devices/device_xiaomi_sunny/tree/alpha-14",
			"common-dt": "",
			"kernel": "https://github.com/Neternels/android_kernel_xiaomi_sunny/tree/staging"
		},
		{
			"maintainer": "eklerismunir",
			"oem": "Xiaomi",
			"device": "Xiaomi Redmi Note 10",
			"filename": "AlphaDroid-14.0-20240807-sunny-gapps-v2.3.zip",
			"download": "https://sourceforge.net/projects/alphadroid-project/files/sunny/AlphaDroid-14.0-20240807-sunny-gapps-v2.3.zip/download",
			"timestamp": 1723067605,
			"md5": "c480e145ea96bc47f76bda2068c74678",
			"sha256": "b0f79a9c4c4b89228ca696d476e8e959cb3c5debdebcf84334c4c0c16cb6dde4",
			"size": 2396527024,
			"version": "2.3",
			"buildtype": "gapps",
			"forum": "https://t.me/alphadroid_chat",
			"gapps": "",
			"firmware": "",
			"modem": "",
			"bootloader": "",
			"recovery": "",
			"paypal": "",
			"telegram": "https://t.me/shawkbuilddiscussion",
			"dt": "https://github.com/AlphaDroid-devices/device_xiaomi_sunny/tree/alpha-14",
			"common-dt": "",
			"kernel": "https://github.com/Neternels/android_kernel_xiaomi_sunny/tree/staging"
		}
	]
}
