{
	"response": [
		{
			"maintainer": "MrTopiA",
			"oem": "Redmi",
			"device": "Poco X4 Pro",
			"filename": "AlphaDroid-14.0-20240520-veux-gapps-v2.1.zip",
			"download": "https://sourceforge.net/projects/alphadroid-project/files/veux/AlphaDroid-14.0-20240520-veux-gapps-v2.1.zip/download",
			"timestamp": 1716204857,
			"md5": "a45c3b16d1033c50e3435ff37f9116b7",
			"sha256": "5afadd516fdeee9a0d30893124b9b3d548ad35cadc670f328ef7c26d2d2d948b",
			"size": 2005816518,
			"version": "2.1",
			"buildtype": "gapps",
			"forum": "",
			"gapps": "",
			"firmware": "",
			"modem": "",
			"bootloader": "",
			"recovery": "",
			"paypal": "",
			"telegram": "https://t.me/MrTopiA",
			"dt": "https://github.com/AlphaDroid-devices/device_xiaomi_veux",
			"common-dt": "",
			"kernel": "https://github.com/AlphaDroid-devices/kernel_xiaomi_sm6375"
		}
	]
}
